adafruit_circuitpython_progressbar-2.3.20.dist-info/licenses/LICENSE
adafruit_progressbar/__init__.py
adafruit_progressbar/horizontalprogressbar.py
adafruit_progressbar/progressbar.py
adafruit_progressbar/verticalprogressbar.py
adafruit_circuitpython_progressbar-2.3.20.dist-info/METADATA
adafruit_circuitpython_progressbar-2.3.20.dist-info/WHEEL
adafruit_circuitpython_progressbar-2.3.20.dist-info/top_level.txt
adafruit_circuitpython_progressbar-2.3.20.dist-info/RECORD
